clipfx/__init__.py
clipfx/cli.py
clipfx-0.1.1.dist-info/METADATA
clipfx-0.1.1.dist-info/WHEEL
clipfx-0.1.1.dist-info/entry_points.txt
clipfx-0.1.1.dist-info/top_level.txt
clipfx-0.1.1.dist-info/RECORD
