Metadata-Version: 2.4
Name: clipfx
Version: 0.1.1
Summary: Serve a file or stdin via Cloudflare Tunnel
Home-page: https://github.com/yourusername/clipfx
Author: Your Name
Author-email: your@email.com
License: MIT
Classifier: Programming Language :: Python :: 3
Classifier: License :: OSI Approved :: MIT License
Classifier: Operating System :: OS Independent
Requires-Python: >=3.7
